Metadata-Version: 1.2
Name: pbliuutils
Version: 1.0.1
Summary: A util for file operation
Home-page: https://www.python.org/
Author: pbliu
Author-email: sbpt123456@126.com
License: MIT
Project-URL: Documentation, https://packaging.python.org/tutorials/distributing-packages/
Project-URL: Funding, https://donate.pypi.org
Project-URL: Source, https://github.com/pypa/sampleproject/
Project-URL: Tracker, https://github.com/pypa/sampleproject/issues
Keywords: simpleitk pickle
Platform: UNKNOWN
Requires-Python: >=3
